{
  "strategies": {
    "crypto_trend": {
      "enabled": true,
      "lastTradeTime": 1773263519695,
      "trades": [
        {
          "symbol": "sui",
          "direction": "long",
          "entryPrice": 0.956126,
          "size": 320,
          "confidence": 0.8,
          "reason": "Trend: 2.4%, RSI: 48.9",
          "exitPrice": 0.8594809572072158,
          "pnl": -32.3455420035549,
          "mode": "practice",
          "exitTime": 1772760529480,
          "timestamp": 1772760529480
        },
        {
          "symbol": "solana",
          "direction": "long",
          "entryPrice": 88.47,
          "size": 320,
          "confidence": 0.8,
          "reason": "Trend: 2.7%, RSI: 49.4",
          "exitPrice": 105.85329731421425,
          "pnl": 62.87617430257214,
          "mode": "practice",
          "exitTime": 1772782140744,
          "timestamp": 1772782140744
        },
        {
          "symbol": "sui",
          "direction": "long",
          "entryPrice": 0.948163,
          "size": 320,
          "confidence": 0.8,
          "reason": "Trend: 2.7%, RSI: 40.4",
          "exitPrice": 0.903642464459391,
          "pnl": -15.025445385439937,
          "mode": "practice",
          "exitTime": 1772803752315,
          "timestamp": 1772803752315
        },
        {
          "symbol": "sui",
          "direction": "long",
          "entryPrice": 0.899598,
          "size": 320,
          "confidence": 0.8,
          "reason": "Trend: 7.9%, RSI: 38.3",
          "exitPrice": 0.8193815423857269,
          "pnl": -28.534152406483102,
          "mode": "practice",
          "exitTime": 1772825560272,
          "timestamp": 1772825560272
        },
        {
          "symbol": "solana",
          "direction": "long",
          "entryPrice": 84.58,
          "size": 320,
          "confidence": 0.8,
          "reason": "Trend: 8.5%, RSI: 37.1",
          "exitPrice": 97.61654224643937,
          "pnl": 49.32245825089382,
          "mode": "practice",
          "exitTime": 1772865881160,
          "timestamp": 1772865881160
        },
        {
          "symbol": "pepe",
          "direction": "long",
          "entryPrice": 0.00000326,
          "size": 320,
          "confidence": 0.8,
          "reason": "Trend: 4.3%, RSI: 39.2",
          "exitPrice": 0.0000033890996389083137,
          "pnl": 12.672357193454076,
          "mode": "practice",
          "exitTime": 1772911340692,
          "timestamp": 1772911340692
        },
        {
          "symbol": "solana",
          "direction": "long",
          "entryPrice": 83.14,
          "size": 320,
          "confidence": 0.8,
          "reason": "Trend: 2.5%, RSI: 49.7",
          "exitPrice": 84.2487965477098,
          "pnl": 4.267679760249408,
          "mode": "practice",
          "exitTime": 1772932972929,
          "timestamp": 1772932972929
        },
        {
          "symbol": "toncoin",
          "direction": "long",
          "entryPrice": 2.45,
          "size": 320,
          "confidence": 0.8,
          "reason": "Trend: 2.1%, RSI: 45.5",
          "exitPrice": 2.993326068789765,
          "pnl": 70.9650375562142,
          "mode": "practice",
          "exitTime": 1772954855913,
          "timestamp": 1772954855913
        },
        {
          "symbol": "solana",
          "direction": "long",
          "entryPrice": 83.83,
          "size": 320,
          "confidence": 0.8,
          "reason": "Trend: 2.1%, RSI: 47.1",
          "exitPrice": 98.72301758206798,
          "pnl": 56.85035937327633,
          "mode": "practice",
          "exitTime": 1772977211559,
          "timestamp": 1772977211559
        },
        {
          "symbol": "sui",
          "direction": "long",
          "entryPrice": 0.880723,
          "size": 320,
          "confidence": 0.8,
          "reason": "Trend: 4.0%, RSI: 44.7",
          "exitPrice": 0.9983325385375965,
          "pnl": 42.731996702744084,
          "mode": "practice",
          "exitTime": 1773004320186,
          "timestamp": 1773004320186
        },
        {
          "symbol": "sui",
          "direction": "long",
          "entryPrice": 0.72,
          "size": 320,
          "confidence": 0.8,
          "reason": "Trend: 3.7%, RSI: 50.6",
          "exitPrice": 0.7943516454745845,
          "pnl": 33.04517576648202,
          "mode": "practice",
          "exitTime": 1773027609913,
          "timestamp": 1773027609913
        },
        {
          "symbol": "popcat",
          "direction": "long",
          "entryPrice": 0.051791,
          "size": 320,
          "confidence": 0.8,
          "reason": "Trend: 8.0%, RSI: 61.5",
          "exitPrice": 0.04957420474691373,
          "pnl": -13.696867814631979,
          "mode": "practice",
          "exitTime": 1773053906204,
          "timestamp": 1773053906204
        },
        {
          "symbol": "wif",
          "direction": "long",
          "entryPrice": 0.85,
          "size": 320,
          "confidence": 0.8,
          "reason": "Trend: 7.7%, RSI: 45.1",
          "exitPrice": 0.8562317864411907,
          "pnl": 2.3460843072717807,
          "mode": "practice",
          "exitTime": 1773077593617,
          "timestamp": 1773077593617
        },
        {
          "symbol": "solana",
          "direction": "long",
          "entryPrice": 86.03,
          "size": 320,
          "confidence": 0.8,
          "reason": "Trend: 9.6%, RSI: 65.0",
          "exitPrice": 94.75601694006969,
          "pnl": 32.45757783124837,
          "mode": "practice",
          "exitTime": 1773104472155,
          "timestamp": 1773104472155
        },
        {
          "symbol": "sui",
          "direction": "long",
          "entryPrice": 0.72,
          "size": 320,
          "confidence": 0.8,
          "reason": "Trend: 3.1%, RSI: 41.0",
          "exitPrice": 0.7494905271575605,
          "pnl": 13.106900958915801,
          "mode": "practice",
          "exitTime": 1773131862820,
          "timestamp": 1773131862820
        },
        {
          "symbol": "sui",
          "direction": "long",
          "entryPrice": 0.964975,
          "size": 320,
          "confidence": 0.8,
          "reason": "Trend: 9.7%, RSI: 67.5",
          "exitPrice": 1.1921400005622023,
          "pnl": 75.33127819881834,
          "mode": "practice",
          "exitTime": 1773156703971,
          "timestamp": 1773156703971
        },
        {
          "symbol": "sui",
          "direction": "long",
          "entryPrice": 0.962216,
          "size": 320,
          "confidence": 0.8,
          "reason": "Trend: 2.2%, RSI: 42.9",
          "exitPrice": 1.0149943294779176,
          "pnl": 17.55226002574645,
          "mode": "practice",
          "exitTime": 1773181864829,
          "timestamp": 1773181864829
        },
        {
          "symbol": "sui",
          "direction": "long",
          "entryPrice": 0.956173,
          "size": 320,
          "confidence": 0.8,
          "reason": "Trend: 2.6%, RSI: 53.2",
          "exitPrice": 0.8267077456267343,
          "pnl": -43.32780929752779,
          "mode": "practice",
          "exitTime": 1773203925855,
          "timestamp": 1773203925855
        },
        {
          "symbol": "solana",
          "direction": "long",
          "entryPrice": 85.37,
          "size": 320,
          "confidence": 0.8,
          "reason": "Trend: 2.4%, RSI: 47.1",
          "exitPrice": 95.75201504850862,
          "pnl": 38.915834784148515,
          "mode": "practice",
          "exitTime": 1773226343229,
          "timestamp": 1773226343229
        },
        {
          "symbol": "solana",
          "direction": "long",
          "entryPrice": 86.51,
          "size": 320,
          "confidence": 0.8,
          "reason": "Trend: 2.1%, RSI: 55.4",
          "exitPrice": 106.06498769156394,
          "pnl": 72.33378870998102,
          "mode": "practice",
          "exitTime": 1773250671279,
          "timestamp": 1773250671279
        },
        {
          "symbol": "bitcoin",
          "direction": "long",
          "entryPrice": 70816,
          "size": 604.122660517308,
          "confidence": 0.805496880689744,
          "reason": "Trend: bullish, 100% strength, 100% aligned",
          "exitPrice": 87267.01422367993,
          "pnl": 140.3415962638047,
          "mode": "live",
          "exitTime": 1773261738112,
          "timestamp": 1773261738112
        },
        {
          "symbol": "bitcoin",
          "direction": "short",
          "entryPrice": 70788,
          "size": 11.29374144274084,
          "confidence": 0.5128856241026721,
          "reason": "Trend: neutral, 100% strength, 0% aligned",
          "exitPrice": 86154.8025507541,
          "pnl": 2.4516682885498566,
          "mode": "live",
          "exitTime": 1773262919540,
          "timestamp": 1773262919540
        },
        {
          "symbol": "bitcoin",
          "direction": "short",
          "entryPrice": 70743,
          "size": 10.852234386572244,
          "confidence": 0.49283534907230897,
          "reason": "Trend: neutral, 100% strength, 0% aligned",
          "exitPrice": 77012.99148032648,
          "pnl": 0.961839576301742,
          "mode": "live",
          "exitTime": 1773263519695,
          "timestamp": 1773263519695
        }
      ],
      "wonTrades": 18,
      "lostTrades": 5,
      "totalPnl": 595.6002509430349
    },
    "crypto_contrarian": {
      "enabled": true,
      "lastTradeTime": 1773263519698,
      "trades": [
        {
          "symbol": "sui",
          "direction": "long",
          "entryPrice": 0.987788,
          "size": 216,
          "confidence": 0.6,
          "reason": "Bullish RSI divergence detected",
          "exitPrice": 1.035102634610138,
          "pnl": 10.346310216149417,
          "mode": "live-fallback",
          "exitTime": 1773261043717,
          "timestamp": 1773261043717
        },
        {
          "symbol": "dogecoin",
          "direction": "long",
          "entryPrice": 0.093748,
          "size": 8.808,
          "confidence": 0.6,
          "reason": "Bullish RSI divergence detected",
          "exitPrice": 0.08699432702620515,
          "pnl": -0.6345346199725331,
          "mode": "live",
          "exitTime": 1773262919540,
          "timestamp": 1773262919540
        },
        {
          "symbol": "solana",
          "direction": "long",
          "entryPrice": 87.52,
          "size": 8.808,
          "confidence": 0.6,
          "reason": "Bullish RSI divergence detected",
          "exitPrice": 83.56286652539387,
          "pnl": -0.3982453341445472,
          "mode": "live",
          "exitTime": 1773263519698,
          "timestamp": 1773263519698
        }
      ],
      "wonTrades": 1,
      "lostTrades": 2,
      "totalPnl": 9.313530262032337
    },
    "crypto_momentum": {
      "enabled": true,
      "lastTradeTime": 1773263219613,
      "trades": [
        {
          "symbol": "bitcoin",
          "direction": "long",
          "entryPrice": 71250,
          "size": 247.10115555982358,
          "confidence": 0.8236705185327453,
          "reason": "Momentum: 0.5% gain, RSI: 54, Pattern: reversal_up",
          "exitPrice": 68518.41181115572,
          "pnl": -9.473383831255967,
          "mode": "live",
          "exitTime": 1773261043718,
          "timestamp": 1773261043718
        },
        {
          "symbol": "solana",
          "direction": "long",
          "entryPrice": 87.39,
          "size": 8.317188140643793,
          "confidence": 0.7554212661801811,
          "reason": "Momentum: -0.3% gain, RSI: 55, Pattern: reversal_down",
          "exitPrice": 106.38142193451537,
          "pnl": 1.8074748745590308,
          "mode": "live",
          "exitTime": 1773263219613,
          "timestamp": 1773263219613
        }
      ],
      "wonTrades": 1,
      "lostTrades": 1,
      "totalPnl": -7.665908956696937
    },
    "poly_momentum": {
      "enabled": true,
      "lastTradeTime": 1773258139023,
      "trades": [
        {
          "symbol": "Will the Seattle Kraken win the 2026 NHL Stanley Cup?",
          "direction": "no",
          "entryPrice": 0.9925,
          "size": 105,
          "confidence": 0.7,
          "reason": "Momentum: Vol: $459.8K, Prob: 1%, Vol: $459.8K",
          "exitPrice": 1.213529006574372,
          "pnl": 23.383421350437327,
          "mode": "practice",
          "exitTime": 1772760529481,
          "timestamp": 1772760529481
        },
        {
          "symbol": "Will the Seattle Kraken win the 2026 NHL Stanley Cup?",
          "direction": "no",
          "entryPrice": 0.993,
          "size": 105,
          "confidence": 0.7,
          "reason": "Momentum: Vol: $460.0K, Prob: 1%, Vol: $460.0K",
          "exitPrice": 1.1413515630382391,
          "pnl": 15.686721167185404,
          "mode": "practice",
          "exitTime": 1772767733137,
          "timestamp": 1772767733137
        },
        {
          "symbol": "Will the Seattle Kraken win the 2026 NHL Stanley Cup?",
          "direction": "no",
          "entryPrice": 0.993,
          "size": 105,
          "confidence": 0.7,
          "reason": "Momentum: Vol: $460.1K, Prob: 1%, Vol: $460.1K",
          "exitPrice": 0.8528395109952294,
          "pnl": -14.820595514099612,
          "mode": "practice",
          "exitTime": 1772774937063,
          "timestamp": 1772774937063
        },
        {
          "symbol": "Will the Seattle Kraken win the 2026 NHL Stanley Cup?",
          "direction": "no",
          "entryPrice": 0.993,
          "size": 105,
          "confidence": 0.7,
          "reason": "Momentum: Vol: $460.1K, Prob: 1%, Vol: $460.1K",
          "exitPrice": 1.1018696994704684,
          "pnl": 11.511901756696066,
          "mode": "practice",
          "exitTime": 1772782140744,
          "timestamp": 1772782140744
        },
        {
          "symbol": "Will the Seattle Kraken win the 2026 NHL Stanley Cup?",
          "direction": "no",
          "entryPrice": 0.9935,
          "size": 105,
          "confidence": 0.7,
          "reason": "Momentum: Vol: $460.1K, Prob: 1%, Vol: $460.1K",
          "exitPrice": 1.0238763648935487,
          "pnl": 3.2103858216634173,
          "mode": "practice",
          "exitTime": 1772789344645,
          "timestamp": 1772789344645
        },
        {
          "symbol": "Will the Seattle Kraken win the 2026 NHL Stanley Cup?",
          "direction": "no",
          "entryPrice": 0.9935,
          "size": 105,
          "confidence": 0.7,
          "reason": "Momentum: Vol: $460.3K, Prob: 1%, Vol: $460.3K",
          "exitPrice": 0.9954325366554257,
          "pnl": 0.20424393439324895,
          "mode": "practice",
          "exitTime": 1772796548349,
          "timestamp": 1772796548349
        },
        {
          "symbol": "Will the Seattle Kraken win the 2026 NHL Stanley Cup?",
          "direction": "no",
          "entryPrice": 0.9935,
          "size": 105,
          "confidence": 0.7,
          "reason": "Momentum: Vol: $460.3K, Prob: 1%, Vol: $460.3K",
          "exitPrice": 0.9520466483281641,
          "pnl": -4.381078938643962,
          "mode": "practice",
          "exitTime": 1772803752315,
          "timestamp": 1772803752315
        },
        {
          "symbol": "Will the Seattle Kraken win the 2026 NHL Stanley Cup?",
          "direction": "no",
          "entryPrice": 0.9935,
          "size": 105,
          "confidence": 0.7,
          "reason": "Momentum: Vol: $461.4K, Prob: 1%, Vol: $461.4K",
          "exitPrice": 1.217716206365649,
          "pnl": 23.696730416097786,
          "mode": "practice",
          "exitTime": 1772810956374,
          "timestamp": 1772810956374
        },
        {
          "symbol": "Will the Seattle Kraken win the 2026 NHL Stanley Cup?",
          "direction": "no",
          "entryPrice": 0.9935,
          "size": 105,
          "confidence": 0.7,
          "reason": "Momentum: Vol: $461.9K, Prob: 1%, Vol: $461.9K",
          "exitPrice": 0.9689788963964151,
          "pnl": -2.591561025039178,
          "mode": "practice",
          "exitTime": 1772821358070,
          "timestamp": 1772821358070
        },
        {
          "symbol": "Will the Seattle Kraken win the 2026 NHL Stanley Cup?",
          "direction": "no",
          "entryPrice": 0.9935,
          "size": 105,
          "confidence": 0.7,
          "reason": "Momentum: Vol: $462.0K, Prob: 1%, Vol: $462.0K",
          "exitPrice": 1.199561657950274,
          "pnl": 21.77803128815174,
          "mode": "practice",
          "exitTime": 1772828562078,
          "timestamp": 1772828562078
        },
        {
          "symbol": "Will the Seattle Kraken win the 2026 NHL Stanley Cup?",
          "direction": "no",
          "entryPrice": 0.9935,
          "size": 105,
          "confidence": 0.7,
          "reason": "Momentum: Vol: $462.0K, Prob: 1%, Vol: $462.0K",
          "exitPrice": 0.9123122478970518,
          "pnl": -8.580487137201377,
          "mode": "practice",
          "exitTime": 1772835768277,
          "timestamp": 1772835768277
        },
        {
          "symbol": "Will the Seattle Kraken win the 2026 NHL Stanley Cup?",
          "direction": "no",
          "entryPrice": 0.9925,
          "size": 105,
          "confidence": 0.7,
          "reason": "Momentum: Vol: $466.3K, Prob: 1%, Vol: $466.3K",
          "exitPrice": 0.9416140428834078,
          "pnl": -5.383401004778018,
          "mode": "practice",
          "exitTime": 1772865881162,
          "timestamp": 1772865881162
        },
        {
          "symbol": "Will the Seattle Kraken win the 2026 NHL Stanley Cup?",
          "direction": "no",
          "entryPrice": 0.993,
          "size": 105,
          "confidence": 0.7,
          "reason": "Momentum: Vol: $469.0K, Prob: 1%, Vol: $469.0K",
          "exitPrice": 1.0119371106780721,
          "pnl": 2.0024135158082346,
          "mode": "practice",
          "exitTime": 1772873447826,
          "timestamp": 1772873447826
        },
        {
          "symbol": "Will the Seattle Kraken win the 2026 NHL Stanley Cup?",
          "direction": "no",
          "entryPrice": 0.994,
          "size": 105,
          "confidence": 0.7,
          "reason": "Momentum: Vol: $469.1K, Prob: 1%, Vol: $469.1K",
          "exitPrice": 1.0344919839213056,
          "pnl": 4.2773222452083495,
          "mode": "practice",
          "exitTime": 1772911340694,
          "timestamp": 1772911340694
        },
        {
          "symbol": "Will the Seattle Kraken win the 2026 NHL Stanley Cup?",
          "direction": "no",
          "entryPrice": 0.9945,
          "size": 105,
          "confidence": 0.7,
          "reason": "Momentum: Vol: $469.2K, Prob: 1%, Vol: $469.2K",
          "exitPrice": 1.1163807450780512,
          "pnl": 12.868253628150203,
          "mode": "practice",
          "exitTime": 1772918544316,
          "timestamp": 1772918544316
        },
        {
          "symbol": "Will the Seattle Kraken win the 2026 NHL Stanley Cup?",
          "direction": "no",
          "entryPrice": 0.9945,
          "size": 105,
          "confidence": 0.7,
          "reason": "Momentum: Vol: $469.2K, Prob: 1%, Vol: $469.2K",
          "exitPrice": 1.0726735465036348,
          "pnl": 8.253617277910143,
          "mode": "practice",
          "exitTime": 1772925751148,
          "timestamp": 1772925751148
        },
        {
          "symbol": "Will the Seattle Kraken win the 2026 NHL Stanley Cup?",
          "direction": "no",
          "entryPrice": 0.9945,
          "size": 105,
          "confidence": 0.7,
          "reason": "Momentum: Vol: $469.2K, Prob: 1%, Vol: $469.2K",
          "exitPrice": 1.1515649841281874,
          "pnl": 16.58302999845116,
          "mode": "practice",
          "exitTime": 1772932972931,
          "timestamp": 1772932972931
        },
        {
          "symbol": "Will the Seattle Kraken win the 2026 NHL Stanley Cup?",
          "direction": "no",
          "entryPrice": 0.9945,
          "size": 105,
          "confidence": 0.7,
          "reason": "Momentum: Vol: $469.2K, Prob: 1%, Vol: $469.2K",
          "exitPrice": 1.211991113746284,
          "pnl": 22.96286268814461,
          "mode": "practice",
          "exitTime": 1772943874298,
          "timestamp": 1772943874298
        },
        {
          "symbol": "Will the Seattle Kraken win the 2026 NHL Stanley Cup?",
          "direction": "no",
          "entryPrice": 0.995,
          "size": 105,
          "confidence": 0.7,
          "reason": "Momentum: Vol: $471.3K, Prob: 1%, Vol: $471.3K",
          "exitPrice": 0.9879758046194054,
          "pnl": -0.741246748705971,
          "mode": "practice",
          "exitTime": 1772954855915,
          "timestamp": 1772954855915
        },
        {
          "symbol": "Will the Seattle Kraken win the 2026 NHL Stanley Cup?",
          "direction": "no",
          "entryPrice": 0.995,
          "size": 105,
          "confidence": 0.7,
          "reason": "Momentum: Vol: $472.0K, Prob: 1%, Vol: $472.0K",
          "exitPrice": 0.8674933361665776,
          "pnl": -13.455477087949097,
          "mode": "practice",
          "exitTime": 1772966178724,
          "timestamp": 1772966178724
        },
        {
          "symbol": "Will the Seattle Kraken win the 2026 NHL Stanley Cup?",
          "direction": "no",
          "entryPrice": 0.9945,
          "size": 105,
          "confidence": 0.7,
          "reason": "Momentum: Vol: $472.4K, Prob: 1%, Vol: $472.4K",
          "exitPrice": 0.8797708738872064,
          "pnl": -12.113180735890728,
          "mode": "practice",
          "exitTime": 1772977211560,
          "timestamp": 1772977211560
        },
        {
          "symbol": "Will the Seattle Kraken win the 2026 NHL Stanley Cup?",
          "direction": "no",
          "entryPrice": 0.9945,
          "size": 105,
          "confidence": 0.7,
          "reason": "Momentum: Vol: $472.4K, Prob: 1%, Vol: $472.4K",
          "exitPrice": 0.9601660615515037,
          "pnl": -3.6250010428276616,
          "mode": "practice",
          "exitTime": 1772988832077,
          "timestamp": 1772988832077
        },
        {
          "symbol": "Will the Seattle Kraken win the 2026 NHL Stanley Cup?",
          "direction": "no",
          "entryPrice": 0.9945,
          "size": 105,
          "confidence": 0.7,
          "reason": "Momentum: Vol: $472.8K, Prob: 1%, Vol: $472.8K",
          "exitPrice": 1.1263543558553422,
          "pnl": 13.921274373867181,
          "mode": "practice",
          "exitTime": 1772998748894,
          "timestamp": 1772998748894
        },
        {
          "symbol": "Will the Seattle Kraken win the 2026 NHL Stanley Cup?",
          "direction": "no",
          "entryPrice": 0.9945,
          "size": 105,
          "confidence": 0.7,
          "reason": "Momentum: Vol: $472.9K, Prob: 1%, Vol: $472.9K",
          "exitPrice": 0.9350855615807021,
          "pnl": -6.2730176309967645,
          "mode": "practice",
          "exitTime": 1773009710533,
          "timestamp": 1773009710533
        },
        {
          "symbol": "Will the Seattle Kraken win the 2026 NHL Stanley Cup?",
          "direction": "no",
          "entryPrice": 0.9945,
          "size": 105,
          "confidence": 0.7,
          "reason": "Momentum: Vol: $472.9K, Prob: 1%, Vol: $472.9K",
          "exitPrice": 1.0723719996231782,
          "pnl": 8.221779749053496,
          "mode": "practice",
          "exitTime": 1773020668447,
          "timestamp": 1773020668447
        },
        {
          "symbol": "Will the Seattle Kraken win the 2026 NHL Stanley Cup?",
          "direction": "no",
          "entryPrice": 0.9945,
          "size": 105,
          "confidence": 0.7,
          "reason": "Momentum: Vol: $473.1K, Prob: 1%, Vol: $473.1K",
          "exitPrice": 0.891271975578243,
          "pnl": -10.898886439702856,
          "mode": "practice",
          "exitTime": 1773031649791,
          "timestamp": 1773031649791
        },
        {
          "symbol": "Will the Seattle Kraken win the 2026 NHL Stanley Cup?",
          "direction": "no",
          "entryPrice": 0.9945,
          "size": 105,
          "confidence": 0.7,
          "reason": "Momentum: Vol: $473.7K, Prob: 1%, Vol: $473.7K",
          "exitPrice": 1.2367681961337376,
          "pnl": 25.57884423734784,
          "mode": "practice",
          "exitTime": 1773042610329,
          "timestamp": 1773042610329
        },
        {
          "symbol": "Will the Seattle Kraken win the 2026 NHL Stanley Cup?",
          "direction": "no",
          "entryPrice": 0.995,
          "size": 105,
          "confidence": 0.7,
          "reason": "Momentum: Vol: $477.7K, Prob: 1%, Vol: $477.7K",
          "exitPrice": 1.1396755531886278,
          "pnl": 15.267269431965754,
          "mode": "practice",
          "exitTime": 1773053906205,
          "timestamp": 1773053906205
        },
        {
          "symbol": "Will the Seattle Kraken win the 2026 NHL Stanley Cup?",
          "direction": "no",
          "entryPrice": 0.9945,
          "size": 105,
          "confidence": 0.7,
          "reason": "Momentum: Vol: $478.8K, Prob: 1%, Vol: $478.8K",
          "exitPrice": 1.2258173773148504,
          "pnl": 24.42264918859657,
          "mode": "practice",
          "exitTime": 1773065142310,
          "timestamp": 1773065142310
        },
        {
          "symbol": "Will the Seattle Kraken win the 2026 NHL Stanley Cup?",
          "direction": "no",
          "entryPrice": 0.995,
          "size": 105,
          "confidence": 0.7,
          "reason": "Momentum: Vol: $479.3K, Prob: 1%, Vol: $479.3K",
          "exitPrice": 0.9616499381490227,
          "pnl": -3.5193532606559015,
          "mode": "practice",
          "exitTime": 1773077593619,
          "timestamp": 1773077593619
        },
        {
          "symbol": "Will the Seattle Kraken win the 2026 NHL Stanley Cup?",
          "direction": "no",
          "entryPrice": 0.9945,
          "size": 105,
          "confidence": 0.7,
          "reason": "Momentum: Vol: $479.4K, Prob: 1%, Vol: $479.4K",
          "exitPrice": 1.0979794229168809,
          "pnl": 10.925429267242318,
          "mode": "practice",
          "exitTime": 1773088187166,
          "timestamp": 1773088187166
        },
        {
          "symbol": "Will the Seattle Kraken win the 2026 NHL Stanley Cup?",
          "direction": "no",
          "entryPrice": 0.9945,
          "size": 105,
          "confidence": 0.7,
          "reason": "Momentum: Vol: $479.5K, Prob: 1%, Vol: $479.5K",
          "exitPrice": 1.2381790869942935,
          "pnl": 25.72780707330398,
          "mode": "practice",
          "exitTime": 1773099169973,
          "timestamp": 1773099169973
        },
        {
          "symbol": "Will the Seattle Kraken win the 2026 NHL Stanley Cup?",
          "direction": "no",
          "entryPrice": 0.9945,
          "size": 105,
          "confidence": 0.7,
          "reason": "Momentum: Vol: $479.5K, Prob: 1%, Vol: $479.5K",
          "exitPrice": 1.1258057816840776,
          "pnl": 13.863355532255545,
          "mode": "practice",
          "exitTime": 1773110115458,
          "timestamp": 1773110115458
        },
        {
          "symbol": "Will the Seattle Kraken win the 2026 NHL Stanley Cup?",
          "direction": "no",
          "entryPrice": 0.9945,
          "size": 105,
          "confidence": 0.7,
          "reason": "Momentum: Vol: $479.5K, Prob: 1%, Vol: $479.5K",
          "exitPrice": 1.2339838625531843,
          "pnl": 25.284872366097883,
          "mode": "practice",
          "exitTime": 1773120029955,
          "timestamp": 1773120029955
        },
        {
          "symbol": "Will the Seattle Kraken win the 2026 NHL Stanley Cup?",
          "direction": "no",
          "entryPrice": 0.9955,
          "size": 105,
          "confidence": 0.7,
          "reason": "Momentum: Vol: $500.0K, Prob: 0%, Vol: $500.0K",
          "exitPrice": 1.0811850431422565,
          "pnl": 9.0375987241958,
          "mode": "practice",
          "exitTime": 1773131862821,
          "timestamp": 1773131862821
        },
        {
          "symbol": "Will the Seattle Kraken win the 2026 NHL Stanley Cup?",
          "direction": "no",
          "entryPrice": 0.995,
          "size": 105,
          "confidence": 0.7,
          "reason": "Momentum: Vol: $510.7K, Prob: 1%, Vol: $510.7K",
          "exitPrice": 1.0157620022186178,
          "pnl": 2.190965058246105,
          "mode": "practice",
          "exitTime": 1773144634017,
          "timestamp": 1773144634017
        },
        {
          "symbol": "Will the Seattle Kraken win the 2026 NHL Stanley Cup?",
          "direction": "no",
          "entryPrice": 0.9955,
          "size": 105,
          "confidence": 0.7,
          "reason": "Momentum: Vol: $510.8K, Prob: 0%, Vol: $510.8K",
          "exitPrice": 0.9367521499340165,
          "pnl": -6.196408093348343,
          "mode": "practice",
          "exitTime": 1773156703972,
          "timestamp": 1773156703972
        },
        {
          "symbol": "Will the Seattle Kraken win the 2026 NHL Stanley Cup?",
          "direction": "no",
          "entryPrice": 0.9955,
          "size": 105,
          "confidence": 0.7,
          "reason": "Momentum: Vol: $512.7K, Prob: 0%, Vol: $512.7K",
          "exitPrice": 1.178952399966921,
          "pnl": 19.349575084406524,
          "mode": "practice",
          "exitTime": 1773166074399,
          "timestamp": 1773166074399
        },
        {
          "symbol": "Will the Seattle Kraken win the 2026 NHL Stanley Cup?",
          "direction": "no",
          "entryPrice": 0.9955,
          "size": 105,
          "confidence": 0.7,
          "reason": "Momentum: Vol: $514.0K, Prob: 0%, Vol: $514.0K",
          "exitPrice": 1.025603257866949,
          "pnl": 3.175130161757549,
          "mode": "practice",
          "exitTime": 1773176210899,
          "timestamp": 1773176210899
        },
        {
          "symbol": "Will the Seattle Kraken win the 2026 NHL Stanley Cup?",
          "direction": "no",
          "entryPrice": 0.9945,
          "size": 105,
          "confidence": 0.7,
          "reason": "Momentum: Vol: $514.3K, Prob: 1%, Vol: $514.3K",
          "exitPrice": 0.9752253601041432,
          "pnl": -2.0350298532578917,
          "mode": "practice",
          "exitTime": 1773186181961,
          "timestamp": 1773186181961
        },
        {
          "symbol": "Will the Seattle Kraken win the 2026 NHL Stanley Cup?",
          "direction": "no",
          "entryPrice": 0.9945,
          "size": 105,
          "confidence": 0.7,
          "reason": "Momentum: Vol: $514.3K, Prob: 1%, Vol: $514.3K",
          "exitPrice": 1.090536037942713,
          "pnl": 10.139551517330164,
          "mode": "practice",
          "exitTime": 1773197168112,
          "timestamp": 1773197168112
        },
        {
          "symbol": "Will the Seattle Kraken win the 2026 NHL Stanley Cup?",
          "direction": "no",
          "entryPrice": 0.9955,
          "size": 105,
          "confidence": 0.7,
          "reason": "Momentum: Vol: $514.9K, Prob: 0%, Vol: $514.9K",
          "exitPrice": 1.20854368376454,
          "pnl": 22.470704967631036,
          "mode": "practice",
          "exitTime": 1773209129995,
          "timestamp": 1773209129995
        },
        {
          "symbol": "Will the Seattle Kraken win the 2026 NHL Stanley Cup?",
          "direction": "no",
          "entryPrice": 0.995,
          "size": 105,
          "confidence": 0.7,
          "reason": "Momentum: Vol: $536.1K, Prob: 1%, Vol: $536.1K",
          "exitPrice": 1.1930208328538636,
          "pnl": 20.89667080367406,
          "mode": "practice",
          "exitTime": 1773221009406,
          "timestamp": 1773221009406
        },
        {
          "symbol": "Will the Seattle Kraken win the 2026 NHL Stanley Cup?",
          "direction": "no",
          "entryPrice": 0.9965,
          "size": 105,
          "confidence": 0.7,
          "reason": "Momentum: Vol: $685.7K, Prob: 0%, Vol: $685.7K",
          "exitPrice": 1.202489759151167,
          "pnl": 21.704891832285522,
          "mode": "practice",
          "exitTime": 1773230473675,
          "timestamp": 1773230473675
        },
        {
          "symbol": "Will the Seattle Kraken win the 2026 NHL Stanley Cup?",
          "direction": "no",
          "entryPrice": 0.9955,
          "size": 105,
          "confidence": 0.7,
          "reason": "Momentum: Vol: $686.5K, Prob: 0%, Vol: $686.5K",
          "exitPrice": 1.1257491548702987,
          "pnl": 13.737982181196736,
          "mode": "practice",
          "exitTime": 1773241183574,
          "timestamp": 1773241183574
        },
        {
          "symbol": "Will the Seattle Kraken win the 2026 NHL Stanley Cup?",
          "direction": "no",
          "entryPrice": 0.9955,
          "size": 105,
          "confidence": 0.7,
          "reason": "Momentum: Vol: $686.6K, Prob: 0%, Vol: $686.6K",
          "exitPrice": 1.1287060366152017,
          "pnl": 14.049858206525553,
          "mode": "practice",
          "exitTime": 1773250671281,
          "timestamp": 1773250671281
        },
        {
          "symbol": "Will the Seattle Kraken win the 2026 NHL Stanley Cup?",
          "direction": "no",
          "entryPrice": 0.9955,
          "size": 105,
          "confidence": 0.7,
          "reason": "Momentum: Vol: $686.6K, Prob: 0%, Vol: $686.6K",
          "exitPrice": 1.2229459750414673,
          "pnl": 23.98978139563442,
          "mode": "practice",
          "exitTime": 1773258139023,
          "timestamp": 1773258139023
        }
      ],
      "wonTrades": 33,
      "lostTrades": 14,
      "totalPnl": 395.7602017278143
    },
    "poly_contrarian": {
      "enabled": true,
      "lastTradeTime": 1773255731485,
      "trades": [
        {
          "symbol": "Will the Seattle Kraken win the 2026 NHL Stanley Cup?",
          "direction": "yes",
          "entryPrice": 0.0075,
          "size": 36.9375,
          "confidence": 0.73875,
          "reason": "Contrarian: No at 99% seems overpriced",
          "exitPrice": 0.009274002322922335,
          "pnl": 8.736961440392504,
          "mode": "practice",
          "exitTime": 1772760529481,
          "timestamp": 1772760529481
        },
        {
          "symbol": "Will the Seattle Kraken win the 2026 NHL Stanley Cup?",
          "direction": "yes",
          "entryPrice": 0.007,
          "size": 36.975,
          "confidence": 0.7395,
          "reason": "Contrarian: No at 99% seems overpriced",
          "exitPrice": 0.008432545350236187,
          "pnl": 7.566909189283283,
          "mode": "practice",
          "exitTime": 1772774937064,
          "timestamp": 1772774937064
        },
        {
          "symbol": "Will the Seattle Kraken win the 2026 NHL Stanley Cup?",
          "direction": "yes",
          "entryPrice": 0.0065,
          "size": 37.0125,
          "confidence": 0.7402500000000001,
          "reason": "Contrarian: No at 99% seems overpriced",
          "exitPrice": 0.007625314396625756,
          "pnl": 6.407799862324741,
          "mode": "practice",
          "exitTime": 1772789344646,
          "timestamp": 1772789344646
        },
        {
          "symbol": "Will the Seattle Kraken win the 2026 NHL Stanley Cup?",
          "direction": "yes",
          "entryPrice": 0.0065,
          "size": 37.0125,
          "confidence": 0.7402500000000001,
          "reason": "Contrarian: No at 99% seems overpriced",
          "exitPrice": 0.006159443354280646,
          "pnl": -1.939208130721167,
          "mode": "practice",
          "exitTime": 1772803752315,
          "timestamp": 1772803752315
        },
        {
          "symbol": "Will the Seattle Kraken win the 2026 NHL Stanley Cup?",
          "direction": "yes",
          "entryPrice": 0.0065,
          "size": 37.0125,
          "confidence": 0.7402500000000001,
          "reason": "Contrarian: No at 99% seems overpriced",
          "exitPrice": 0.006601054495613218,
          "pnl": 0.5754276182898843,
          "mode": "practice",
          "exitTime": 1772821358071,
          "timestamp": 1772821358071
        },
        {
          "symbol": "Will the Seattle Kraken win the 2026 NHL Stanley Cup?",
          "direction": "yes",
          "entryPrice": 0.0065,
          "size": 37.0125,
          "confidence": 0.7402500000000001,
          "reason": "Contrarian: No at 99% seems overpriced",
          "exitPrice": 0.006164524045366984,
          "pnl": -1.9102775032083852,
          "mode": "practice",
          "exitTime": 1772835768279,
          "timestamp": 1772835768279
        },
        {
          "symbol": "Will the Seattle Kraken win the 2026 NHL Stanley Cup?",
          "direction": "yes",
          "entryPrice": 0.0075,
          "size": 36.9375,
          "confidence": 0.73875,
          "reason": "Contrarian: No at 99% seems overpriced",
          "exitPrice": 0.006463147393510581,
          "pnl": -5.106499086960389,
          "mode": "practice",
          "exitTime": 1772865881162,
          "timestamp": 1772865881162
        },
        {
          "symbol": "Will the Seattle Kraken win the 2026 NHL Stanley Cup?",
          "direction": "yes",
          "entryPrice": 0.006,
          "size": 37.05,
          "confidence": 0.741,
          "reason": "Contrarian: No at 99% seems overpriced",
          "exitPrice": 0.006386165869026145,
          "pnl": 2.384574241236445,
          "mode": "practice",
          "exitTime": 1772911340694,
          "timestamp": 1772911340694
        },
        {
          "symbol": "Will the Seattle Kraken win the 2026 NHL Stanley Cup?",
          "direction": "yes",
          "entryPrice": 0.0055,
          "size": 37.087500000000006,
          "confidence": 0.7417500000000001,
          "reason": "Contrarian: No at 99% seems overpriced",
          "exitPrice": 0.00657055732979949,
          "pnl": 7.218962721625199,
          "mode": "practice",
          "exitTime": 1772925751149,
          "timestamp": 1772925751149
        },
        {
          "symbol": "Will the Seattle Kraken win the 2026 NHL Stanley Cup?",
          "direction": "yes",
          "entryPrice": 0.0055,
          "size": 37.087500000000006,
          "confidence": 0.7417500000000001,
          "reason": "Contrarian: No at 99% seems overpriced",
          "exitPrice": 0.004757906563504343,
          "pnl": -5.004070968369574,
          "mode": "practice",
          "exitTime": 1772943874299,
          "timestamp": 1772943874299
        },
        {
          "symbol": "Will the Seattle Kraken win the 2026 NHL Stanley Cup?",
          "direction": "yes",
          "entryPrice": 0.005,
          "size": 37.125,
          "confidence": 0.7424999999999999,
          "reason": "Contrarian: No at 100% seems overpriced",
          "exitPrice": 0.004736674955669513,
          "pnl": -1.9551884541538649,
          "mode": "practice",
          "exitTime": 1772960234051,
          "timestamp": 1772960234051
        },
        {
          "symbol": "Will the Seattle Kraken win the 2026 NHL Stanley Cup?",
          "direction": "yes",
          "entryPrice": 0.0055,
          "size": 37.087500000000006,
          "confidence": 0.7417500000000001,
          "reason": "Contrarian: No at 99% seems overpriced",
          "exitPrice": 0.004769024773270039,
          "pnl": -4.929098858426802,
          "mode": "practice",
          "exitTime": 1772977211560,
          "timestamp": 1772977211560
        },
        {
          "symbol": "Will the Seattle Kraken win the 2026 NHL Stanley Cup?",
          "direction": "yes",
          "entryPrice": 0.0055,
          "size": 37.087500000000006,
          "confidence": 0.7417500000000001,
          "reason": "Contrarian: No at 99% seems overpriced",
          "exitPrice": 0.006156470981998592,
          "pnl": 4.426703189976869,
          "mode": "practice",
          "exitTime": 1772993810031,
          "timestamp": 1772993810031
        },
        {
          "symbol": "Will the Seattle Kraken win the 2026 NHL Stanley Cup?",
          "direction": "yes",
          "entryPrice": 0.0055,
          "size": 37.087500000000006,
          "confidence": 0.7417500000000001,
          "reason": "Contrarian: No at 99% seems overpriced",
          "exitPrice": 0.0063651984283969705,
          "pnl": 5.834190311485936,
          "mode": "practice",
          "exitTime": 1773009710535,
          "timestamp": 1773009710535
        },
        {
          "symbol": "Will the Seattle Kraken win the 2026 NHL Stanley Cup?",
          "direction": "yes",
          "entryPrice": 0.0055,
          "size": 37.087500000000006,
          "confidence": 0.7417500000000001,
          "reason": "Contrarian: No at 99% seems overpriced",
          "exitPrice": 0.005933821017255411,
          "pnl": 2.925333995901831,
          "mode": "practice",
          "exitTime": 1773025399516,
          "timestamp": 1773025399516
        },
        {
          "symbol": "Will the Seattle Kraken win the 2026 NHL Stanley Cup?",
          "direction": "yes",
          "entryPrice": 0.0055,
          "size": 37.087500000000006,
          "confidence": 0.7417500000000001,
          "reason": "Contrarian: No at 99% seems overpriced",
          "exitPrice": 0.006313233482167935,
          "pnl": 5.483781230891507,
          "mode": "practice",
          "exitTime": 1773042610330,
          "timestamp": 1773042610330
        },
        {
          "symbol": "Will the Seattle Kraken win the 2026 NHL Stanley Cup?",
          "direction": "yes",
          "entryPrice": 0.005,
          "size": 37.125,
          "confidence": 0.7424999999999999,
          "reason": "Contrarian: No at 100% seems overpriced",
          "exitPrice": 0.005267317328890524,
          "pnl": 1.9848311670121404,
          "mode": "practice",
          "exitTime": 1773059014841,
          "timestamp": 1773059014841
        },
        {
          "symbol": "Will the Seattle Kraken win the 2026 NHL Stanley Cup?",
          "direction": "yes",
          "entryPrice": 0.005,
          "size": 37.125,
          "confidence": 0.7424999999999999,
          "reason": "Contrarian: No at 100% seems overpriced",
          "exitPrice": 0.005035245726582612,
          "pnl": 0.26169951987588785,
          "mode": "practice",
          "exitTime": 1773077593619,
          "timestamp": 1773077593619
        },
        {
          "symbol": "Will the Seattle Kraken win the 2026 NHL Stanley Cup?",
          "direction": "yes",
          "entryPrice": 0.0055,
          "size": 37.087500000000006,
          "confidence": 0.7417500000000001,
          "reason": "Contrarian: No at 99% seems overpriced",
          "exitPrice": 0.0054883098528741596,
          "pnl": -0.07882878755083579,
          "mode": "practice",
          "exitTime": 1773093429080,
          "timestamp": 1773093429080
        },
        {
          "symbol": "Will the Seattle Kraken win the 2026 NHL Stanley Cup?",
          "direction": "yes",
          "entryPrice": 0.0055,
          "size": 37.087500000000006,
          "confidence": 0.7417500000000001,
          "reason": "Contrarian: No at 99% seems overpriced",
          "exitPrice": 0.005880272241726347,
          "pnl": 2.5642448663683495,
          "mode": "practice",
          "exitTime": 1773110115459,
          "timestamp": 1773110115459
        },
        {
          "symbol": "Will the Seattle Kraken win the 2026 NHL Stanley Cup?",
          "direction": "yes",
          "entryPrice": 0.005,
          "size": 37.125,
          "confidence": 0.7424999999999999,
          "reason": "Contrarian: No at 100% seems overpriced",
          "exitPrice": 0.005420672355427269,
          "pnl": 3.123492239047468,
          "mode": "practice",
          "exitTime": 1773125814669,
          "timestamp": 1773125814669
        },
        {
          "symbol": "Will the Seattle Kraken win the 2026 NHL Stanley Cup?",
          "direction": "yes",
          "entryPrice": 0.005,
          "size": 37.125,
          "confidence": 0.7424999999999999,
          "reason": "Contrarian: No at 100% seems overpriced",
          "exitPrice": 0.005316123029095564,
          "pnl": 2.3472134910345637,
          "mode": "practice",
          "exitTime": 1773144634018,
          "timestamp": 1773144634018
        },
        {
          "symbol": "Will the Seattle Kraken win the 2026 NHL Stanley Cup?",
          "direction": "yes",
          "entryPrice": 0.0045,
          "size": 37.1625,
          "confidence": 0.7432500000000001,
          "reason": "Contrarian: No at 100% seems overpriced",
          "exitPrice": 0.004630477701321435,
          "pnl": 1.0775283500795174,
          "mode": "practice",
          "exitTime": 1773160604227,
          "timestamp": 1773160604227
        },
        {
          "symbol": "Will the Seattle Kraken win the 2026 NHL Stanley Cup?",
          "direction": "yes",
          "entryPrice": 0.0045,
          "size": 37.1625,
          "confidence": 0.7432500000000001,
          "reason": "Contrarian: No at 100% seems overpriced",
          "exitPrice": 0.004927631170946013,
          "pnl": 3.531520753395823,
          "mode": "practice",
          "exitTime": 1773176210900,
          "timestamp": 1773176210900
        },
        {
          "symbol": "Will the Seattle Kraken win the 2026 NHL Stanley Cup?",
          "direction": "yes",
          "entryPrice": 0.0055,
          "size": 37.087500000000006,
          "confidence": 0.7417500000000001,
          "reason": "Contrarian: No at 99% seems overpriced",
          "exitPrice": 0.004936677340659738,
          "pnl": -3.798587114233084,
          "mode": "practice",
          "exitTime": 1773190957829,
          "timestamp": 1773190957829
        },
        {
          "symbol": "Will the Seattle Kraken win the 2026 NHL Stanley Cup?",
          "direction": "yes",
          "entryPrice": 0.0045,
          "size": 37.1625,
          "confidence": 0.7432500000000001,
          "reason": "Contrarian: No at 100% seems overpriced",
          "exitPrice": 0.004371668222903177,
          "pnl": -1.0598065925245932,
          "mode": "practice",
          "exitTime": 1773209129997,
          "timestamp": 1773209129997
        },
        {
          "symbol": "Will the Seattle Kraken win the 2026 NHL Stanley Cup?",
          "direction": "yes",
          "entryPrice": 0.005,
          "size": 37.125,
          "confidence": 0.7424999999999999,
          "reason": "Contrarian: No at 100% seems overpriced",
          "exitPrice": 0.004975796768486762,
          "pnl": -0.17970899398579132,
          "mode": "practice",
          "exitTime": 1773223812950,
          "timestamp": 1773223812950
        },
        {
          "symbol": "Will the Seattle Kraken win the 2026 NHL Stanley Cup?",
          "direction": "yes",
          "entryPrice": 0.0045,
          "size": 37.1625,
          "confidence": 0.7432500000000001,
          "reason": "Contrarian: No at 100% seems overpriced",
          "exitPrice": 0.004355154879860097,
          "pnl": -1.1961792838220298,
          "mode": "practice",
          "exitTime": 1773241183575,
          "timestamp": 1773241183575
        },
        {
          "symbol": "Will the Seattle Kraken win the 2026 NHL Stanley Cup?",
          "direction": "yes",
          "entryPrice": 0.0045,
          "size": 37.1625,
          "confidence": 0.7432500000000001,
          "reason": "Contrarian: No at 100% seems overpriced",
          "exitPrice": 0.0043168060730325,
          "pnl": -1.5128765135399396,
          "mode": "practice",
          "exitTime": 1773255731485,
          "timestamp": 1773255731485
        }
      ],
      "wonTrades": 17,
      "lostTrades": 12,
      "totalPnl": 37.7808439007255
    },
    "crypto_degenerate": {
      "enabled": true,
      "lastTradeTime": 0,
      "trades": [],
      "wonTrades": 0,
      "lostTrades": 0,
      "totalPnl": 0
    }
  },
  "portfolio": {
    "totalCapital": 10000,
    "availableCapital": 55.049999999999955,
    "usedCapital": 311.95000000000005,
    "dailyPnl": 1030.7889178769099,
    "totalPnl": 1030.7889178769099,
    "dailyTrades": 104,
    "lastResetDate": "Thu Mar 05 2026"
  },
  "lastRebalance": 1773262919303,
  "isRunning": true,
  "paused": false,
  "pauseReason": null
}